{
  "timestamp": 1752800483.344959,
  "fecha_hora": "2025-07-18 03:01:23",
  "archivo_csv": "muestra_traducciones_10000.csv",
  "metodo": "indice",
  "configuracion": {
    "archivo_catalan": "ca-zh_all_2024_08_05.ca",
    "archivo_chino": "ca-zh_all_2024_08_05.zh",
    "muestras_solicitadas": 10000,
    "total_lineas": 96000000,
    "seed": null,
    "usa_indices": true
  },
  "tiempos": {
    "total_segundos": 11.66,
    "total_minutos": 0.19,
    "lectura_catalan": 1.86,
    "lectura_chino": 1.68,
    "creacion_csv": 0.36,
    "carga_record": 7.4,
    "guardado_record": 0.34
  },
  "resultados": {
    "muestras_extraidas": 9803,
    "muestras_solicitadas": 10000,
    "completado_exitosamente": false
  },
  "estadisticas": {
    "linea_minima": 26715,
    "linea_maxima": 95980028,
    "eficiencia_porcentaje": 98.0,
    "velocidad_muestras_por_segundo": 841.0
  },
  "archivos_fuente": {
    "catalan_existe": true,
    "chino_existe": true,
    "catalan_size_mb": 11745.9,
    "chino_size_mb": 9191.3,
    "indice_catalan_existe": true,
    "indice_chino_existe": true
  },
  "record_stats": {
    "lineas_previas": 1844113,
    "lineas_nuevas": 9803,
    "total_en_record": 1853916,
    "porcentaje_corpus": 1.93
  }
}